README.md
setup.cfg
setup.py
click_path/__init__.py
click_path/core.py
click_path.egg-info/PKG-INFO
click_path.egg-info/SOURCES.txt
click_path.egg-info/dependency_links.txt
click_path.egg-info/requires.txt
click_path.egg-info/top_level.txt