Metadata-Version: 2.1
Name: click-path
Version: 0.0.2
Summary: A library of path-like types for the Click command-line library
Home-page: https://gitlab.com/abraxos/click-path
Author: Eugene Kovalev
Author-email: eugene@kovalev.systems
License: GPL
Project-URL: Documentation, https://gitlab.com/abraxos/click-path
Project-URL: Code, https://gitlab.com/abraxos/click-path
Project-URL: Issue tracker, https://gitlab.com/abraxos/click-path/issues
Keywords: click,path,glob,type,validation
Platform: UNKNOWN
Classifier: Development Status :: 3 - Alpha
Classifier: Intended Audience :: Developers
Classifier: License :: OSI Approved :: GNU General Public License v3 (GPLv3)
Classifier: Operating System :: OS Independent
Classifier: Programming Language :: Python
Classifier: Programming Language :: Python :: 3.6
Classifier: Programming Language :: Python :: 3.7
Classifier: Programming Language :: Python :: 3.8
Requires-Python: >=3.6
Provides-Extra: dev
